olxcleaner/__init__.py
olxcleaner/__version__.py
olxcleaner/errorstore.py
olxcleaner/exceptions.py
olxcleaner/reporting.py
olxcleaner/utils.py
olxcleaner/validate.py
olxcleaner/entries/__init__.py
olxcleaner/entries/edxcleaner.py
olxcleaner/entries/edxreporter.py
olxcleaner/loader/__init__.py
olxcleaner/loader/policy.py
olxcleaner/loader/policy_exceptions.py
olxcleaner/loader/xml.py
olxcleaner/loader/xml_exceptions.py
olxcleaner/objects/__init__.py
olxcleaner/objects/chapter.py
olxcleaner/objects/common.py
olxcleaner/objects/course.py
olxcleaner/objects/discussion.py
olxcleaner/objects/draganddropv2.py
olxcleaner/objects/html.py
olxcleaner/objects/lti.py
olxcleaner/objects/lti_consumer.py
olxcleaner/objects/openassessment.py
olxcleaner/objects/problem.py
olxcleaner/objects/sequential.py
olxcleaner/objects/vertical.py
olxcleaner/objects/video.py
olxcleaner/objects/wiki.py
olxcleaner/parser/__init__.py
olxcleaner/parser/parser_exceptions.py
olxcleaner/parser/policy.py
olxcleaner/parser/slowvalidators.py
olxcleaner/parser/validators.py
olxcleaner-0.3.0.dist-info/LICENSE
olxcleaner-0.3.0.dist-info/METADATA
olxcleaner-0.3.0.dist-info/WHEEL
olxcleaner-0.3.0.dist-info/entry_points.txt
olxcleaner-0.3.0.dist-info/top_level.txt
olxcleaner-0.3.0.dist-info/RECORD
