Metadata-Version: 2.1
Name: olxcleaner
Version: 0.3.0
Summary: Tool to scan Open edX courses for various errors
Home-page: https://github.com/openedx/olxcleaner
Author: Jolyon Bloomfield
Author-email: jolyon@mit.edu
License: LICENSE
Keywords: edx
Classifier: Intended Audience :: Education
Classifier: Topic :: Education :: Computer Aided Instruction (CAI)
Classifier: Development Status :: 4 - Beta
Classifier: Programming Language :: Python :: 3.8
Classifier: Programming Language :: Python :: 3.11
Classifier: Programming Language :: Python :: 3.12
Classifier: License :: OSI Approved :: GNU General Public License v3 (GPLv3)
Classifier: Operating System :: OS Independent
Requires-Python: ~=3.6
License-File: LICENSE
Requires-Dist: lxml
Requires-Dist: python-dateutil
Requires-Dist: pytz
Requires-Dist: pylatexenc
